blfs_manager/__init__.py
blfs_manager/blfspm.py
blfs_manager/bootstrapper.py
blfs_manager/commands.py
blfs_manager/define.py
blfs_manager/utils.py
blfs_pm-1.0.3.dist-info/AUTHORS.md
blfs_pm-1.0.3.dist-info/LICENSE
blfs_pm-1.0.3.dist-info/METADATA
blfs_pm-1.0.3.dist-info/WHEEL
blfs_pm-1.0.3.dist-info/entry_points.txt
blfs_pm-1.0.3.dist-info/top_level.txt
blfs_pm-1.0.3.dist-info/RECORD
