Metadata-Version: 2.1
Name: blfs-pm
Version: 1.0.3
Summary: Package manager for Beyond Linux from Scratch (BLFS) system
Home-page: https://github.com/ahron-maslin/BLFS-automation
Maintainer: Aharon Maslin
Maintainer-email: aronmas613@gmail.com
License: LGPL
Keywords: BLFS,LFS,Package Manager,automation
Platform: Linux
Classifier: Development Status :: 4 - Beta
Classifier: Environment :: Console
Classifier: Intended Audience :: End Users/Desktop
Classifier: License :: OSI Approved :: GNU Lesser General Public License v3 or later (LGPLv3+)
Classifier: Operating System :: OS Independent
Classifier: Programming Language :: Python :: 3.8
Classifier: Programming Language :: Python :: Implementation :: CPython
Classifier: Programming Language :: Python :: Implementation :: PyPy
Classifier: Programming Language :: Python
Classifier: Topic :: Education
License-File: LICENSE
License-File: AUTHORS.md
Requires-Dist: beautifulsoup4 (==4.12.2)
Requires-Dist: bs4 (==0.0.1)
Requires-Dist: certifi (==2022.12.7)
Requires-Dist: charset-normalizer (==3.1.0)
Requires-Dist: idna (==3.4)
Requires-Dist: requests (==2.31.0)
Requires-Dist: soupsieve (==2.4)
Requires-Dist: termcolor (==2.2.0)
Requires-Dist: urllib3 (==1.26.15)
Requires-Dist: wget (==3.2)
Provides-Extra: dev
